LICENSE
MANIFEST.in
README.md
README.rst
setup.cfg
setup.py
coldstart/__init__.py
coldstart/build.py
coldstart/parse.py
coldstart/query.py
coldstart.egg-info/PKG-INFO
coldstart.egg-info/SOURCES.txt
coldstart.egg-info/dependency_links.txt
coldstart.egg-info/requires.txt
coldstart.egg-info/top_level.txt
coldstart/__pycache__/__init__.cpython-37.pyc
coldstart/__pycache__/build.cpython-37.pyc
coldstart/__pycache__/builder.cpython-37.pyc
coldstart/__pycache__/parse.cpython-37.pyc
coldstart/__pycache__/parser.cpython-37.pyc
coldstart/__pycache__/query.cpython-37.pyc
coldstart/query_bank/.gitkeep
coldstart/query_bank/testQuery1.sql
coldstart/query_bank/testQuery2.sql
coldstart/query_bank/testQuery3.sql
coldstart/query_bank/testQuery4.sql
coldstart/query_bank/testQuery5.sql
coldstart/query_bank/testQuery6.sql