Metadata-Version: 2.1
Name: coldstart
Version: 0.1.0
Summary: A package for automatic data curation and feature engineering
Home-page: https://github.com/cvs-health/coldstart
Author: Ferrante, Piero
Author-email: FerranteP@aetna.com
License: Apache 2.0
Platform: UNKNOWN
Requires-Python: >=3.7
License-File: LICENSE
